rnutil/__init__.py
rnutil/datasets.py
rnutil/logistic1d.py
rnutil/metrics.py
rnutil/numpy.py
rnutil/plot.py
rnutil/plot_classification.py
rnutil/plot_logistic.py
rnutil/plot_regression.py
rnutil/data/2_clases_simple.csv
rnutil/data/6_clases_dificil.csv
rnutil/data/circulos.csv
rnutil/data/diabetes.csv
rnutil/data/ecoli.csv
rnutil/data/godzilla.jpg
rnutil/data/iris.csv
rnutil/data/lena.png
rnutil/data/lena_gray.png
rnutil/data/mario.jpg
rnutil/data/mercedes.jpg
rnutil/data/moons.csv
rnutil/data/moons_mis-scaled.csv
rnutil/data/study_logistic.csv
rnutil/data/study_logistic_2d.csv
rnutil/data/study_regression_2d_small.csv
rnutil/data/study_regression_small.csv
rnutil/data/titanic.csv
rnutil/data/who_life_expectancy.csv
rnutil/data/who_life_expectancy_no_missing.csv
rnutil/data/who_life_expectancy_no_missing_numeric.csv
rnutil-0.4.4.dist-info/LICENSE
rnutil-0.4.4.dist-info/METADATA
rnutil-0.4.4.dist-info/WHEEL
rnutil-0.4.4.dist-info/top_level.txt
rnutil-0.4.4.dist-info/RECORD
